simple_assertions/__init__.py
simple_assertions/helper.py
simple_assertions-0.3.0.dist-info/LICENSE
simple_assertions-0.3.0.dist-info/METADATA
simple_assertions-0.3.0.dist-info/WHEEL
simple_assertions-0.3.0.dist-info/top_level.txt
simple_assertions-0.3.0.dist-info/RECORD
