Metadata-Version: 2.1
Name: simple-assertions
Version: 0.3.0
Summary: Assertion library (skeleton) inspired from `assertpy` but without batteries
Home-page: https://github.com/ninadmhatre/simple-assertions
Author: Ninad Mhatre
Author-email: ninad.mhatre@gmail.com
License: MIT
Download-URL: https://github.com/ninadmhatre/simple-assertions/archive/0.3.0.tar.gz
Keywords: test,testing,assert,check,assertion,delayed-assertions,delayedassertions,simple-assertions,simpleassertions,nose,nosetests,unittest
Platform: UNKNOWN
Classifier: Development Status :: 4 - Beta
Classifier: Intended Audience :: Developers
Classifier: Topic :: Software Development :: Testing
Classifier: License :: OSI Approved :: BSD License
Classifier: Natural Language :: English
Classifier: Operating System :: OS Independent
Classifier: Programming Language :: Python :: 3
Classifier: Programming Language :: Python :: 3.5
Classifier: Programming Language :: Python :: 3.6
Classifier: Programming Language :: Python :: 3.7
Classifier: Programming Language :: Python :: 3.8
Classifier: Programming Language :: Python :: 3.9
Requires-Python: >=3.5
